argsupport.py
argsupport-0.0.1.dist-info/LICENSE.md
argsupport-0.0.1.dist-info/METADATA
argsupport-0.0.1.dist-info/WHEEL
argsupport-0.0.1.dist-info/top_level.txt
argsupport-0.0.1.dist-info/RECORD
