Metadata-Version: 2.1
Name: argsupport
Version: 0.0.1
Summary: Supporting argparse
Home-page: http://github.com/ddmee/argsupport
Author: Donal Mee
Author-email: mee.donal@gmail.com
License: UNKNOWN
Platform: UNKNOWN
Classifier: Programming Language :: Python :: 2
Classifier: Programming Language :: Python :: 3
Classifier: License :: OSI Approved :: MIT License
Classifier: Operating System :: OS Independent
